syngate/__init__.py
syngate/main.py
syngate/session_id_generator.py
syngate/syngate_withopen/__init__.py
syngate/syngate_withopen/archive.py
syngate/syngate_withopen/main.py
syngate/syngate_withopen/mdb_ScreenBuffer.py
syngate/syngate_withopen/mdb_control_file_visibility.py
syngate/syngate_withopen/mdb_core.py
syngate/syngate_withopen/mdb_date_change.py
syngate/syngate_withopen/mdb_future_datetime.py
syngate/syngate_withopen/mdb_how_long.py
syngate/syngate_withopen/mdb_loop_progress.py
syngate/syngate_withopen/mdb_max_clear.py
syngate/syngate_withopen/mdb_mini_guide.py
syngate/syngate_withopen/mdb_others.py
syngate/syngate_withopen/mdb_pretty_print.py
syngate/syngate_withopen/mdb_session_id_generator.py
syngate/syngate_withopen/mdb_validations.py
syngate/syngate_withopen/mdb_wait_queue.py
syngate-4.0.1.dist-info/licenses/LICENSE
syngate-4.0.1.dist-info/METADATA
syngate-4.0.1.dist-info/WHEEL
syngate-4.0.1.dist-info/top_level.txt
syngate-4.0.1.dist-info/RECORD
