Metadata-Version: 2.4
Name: syngate
Version: 4.0.1
Summary: File-Based Queue, Scheduler, and Mutex Locker for Python (Windows, macOS, Linux)
Author: henry
Author-email: osas2henry@gmail.com
Classifier: Programming Language :: Python :: 3
Classifier: Operating System :: OS Independent
Classifier: License :: OSI Approved :: MIT License
Requires-Python: >=3.7
License-File: LICENSE
Dynamic: author
Dynamic: author-email
Dynamic: classifier
Dynamic: description
Dynamic: description-content-type
Dynamic: license-file
Dynamic: requires-python
Dynamic: summary
